{
    "110": {
        "number": "110",
        "name": "النصر",
        "name_latin": "An-Nasr",
        "number_of_ayah": "3",
        "text": {
            "1": "اِذَا جَاۤءَ نَصْرُ اللّٰهِ وَالْفَتْحُۙ",
            "2": "وَرَاَيْتَ النَّاسَ يَدْخُلُوْنَ فِيْ دِيْنِ اللّٰهِ اَفْوَاجًاۙ",
            "3": "فَسَبِّحْ بِحَمْدِ رَبِّكَ وَاسْتَغْفِرْهُۗ اِنَّهٗ كَانَ تَوَّابًا ࣖ"
        },
        "translations": {
            "id": {
                "name": "Partulungan",
                "text": {
                    "1": "Apabila humantang na in partulungan sin Allahu ta'ala iban pag-ukab sin Makkah kaymu iban manga mu'min.",
                    "2": "Iban kakitaan mu na in manusiya sumud na sila pa Agama sin Allahu ta'ala nagbaba'an-ba'an.",
                    "3": "Na, pataura na in pagsukul mu pa Tuhan nangatas kaymu, iban pataura in panasibi mu sin pamudji mu kaniya iban pangayua in ka-ampunan niya kaymu iban ha manga ummat mu. Karna bunnal tuud in Allahu ta'ala Tawwab (Mananawbat iban mananayma pag-tawbat)."
                }
            }
        }
    }
}